LatencyMap.py
pylatencymap-1.3.1.dist-info/licenses/LICENSE
pylatencymap-1.3.1.dist-info/METADATA
pylatencymap-1.3.1.dist-info/WHEEL
pylatencymap-1.3.1.dist-info/entry_points.txt
pylatencymap-1.3.1.dist-info/top_level.txt
pylatencymap-1.3.1.dist-info/RECORD
