Metadata-Version: 2.4
Name: PyLatencyMap
Version: 1.3.1
Summary: Visualize latency distributions over time in your terminal with frequency and intensity heat maps.
Author-email: Luca Canali <Luca.Canali@cern.ch>
License:                                  Apache License
Project-URL: Homepage, https://github.com/LucaCanali/PyLatencyMap
Project-URL: Repository, https://github.com/LucaCanali/PyLatencyMap
Project-URL: Issues, https://github.com/LucaCanali/PyLatencyMap/issues
Project-URL: Changelog, https://github.com/LucaCanali/PyLatencyMap/releases
Keywords: latency,heatmap,cli,performance,histogram,monitoring,observability
Classifier: Development Status :: 4 - Beta
Classifier: Environment :: Console
Classifier: Intended Audience :: Developers
Classifier: Intended Audience :: System Administrators
Classifier: License :: OSI Approved :: Apache Software License
Classifier: Operating System :: OS Independent
Classifier: Programming Language :: Python
Classifier: Programming Language :: Python :: 3
Classifier: Programming Language :: Python :: 3.9
Classifier: Programming Language :: Python :: 3.10
Classifier: Programming Language :: Python :: 3.11
Classifier: Programming Language :: Python :: 3.12
Classifier: Topic :: System :: Monitoring
Classifier: Topic :: Utilities
Classifier: Natural Language :: English
Requires-Python: >=3.9
License-File: LICENSE
Dynamic: license-file
